agent/__init__.py
agent/__main__.py
agent/adapters/__init__.py
agent/adapters/azure_ml_adapter.py
agent/adapters/cua_adapter.py
agent/adapters/huggingfacelocal_adapter.py
agent/adapters/human_adapter.py
agent/adapters/mlxvlm_adapter.py
agent/adapters/models/__init__.py
agent/adapters/models/generic.py
agent/adapters/models/internvl.py
agent/adapters/models/opencua.py
agent/adapters/models/qwen2_5_vl.py
agent/agent.py
agent/callbacks/__init__.py
agent/callbacks/base.py
agent/callbacks/budget_manager.py
agent/callbacks/image_retention.py
agent/callbacks/logging.py
agent/callbacks/operator_validator.py
agent/callbacks/otel.py
agent/callbacks/pii_anonymization.py
agent/callbacks/prompt_instructions.py
agent/callbacks/telemetry.py
agent/callbacks/trajectory_saver.py
agent/cli.py
agent/computers/__init__.py
agent/computers/base.py
agent/computers/cua.py
agent/computers/custom.py
agent/decorators.py
agent/human_tool/__init__.py
agent/human_tool/__main__.py
agent/human_tool/server.py
agent/human_tool/ui.py
agent/integrations/hud/__init__.py
agent/integrations/hud/agent.py
agent/integrations/hud/proxy.py
agent/loops/__init__.py
agent/loops/anthropic.py
agent/loops/base.py
agent/loops/composed_grounded.py
agent/loops/fara/__init__.py
agent/loops/fara/config.py
agent/loops/fara/helpers.py
agent/loops/fara/schema.py
agent/loops/gelato.py
agent/loops/gemini.py
agent/loops/generic_vlm.py
agent/loops/glm45v.py
agent/loops/gta1.py
agent/loops/holo.py
agent/loops/internvl.py
agent/loops/model_types.csv
agent/loops/moondream3.py
agent/loops/omniparser.py
agent/loops/openai.py
agent/loops/opencua.py
agent/loops/uiins.py
agent/loops/uitars.py
agent/loops/uitars2.py
agent/playground/__init__.py
agent/playground/server.py
agent/proxy/examples.py
agent/proxy/handlers.py
agent/responses.py
agent/tools/__init__.py
agent/tools/base.py
agent/tools/browser_tool.py
agent/types.py
agent/ui/__init__.py
agent/ui/__main__.py
agent/ui/gradio/__init__.py
agent/ui/gradio/app.py
cua_agent-0.7.12.dist-info/METADATA
cua_agent-0.7.12.dist-info/WHEEL
cua_agent-0.7.12.dist-info/entry_points.txt
cua_agent-0.7.12.dist-info/RECORD
