Metadata-Version: 2.1
Name: cua-agent
Version: 0.7.12
Summary: Cua (Computer Use) Agent for AI-driven computer interaction
Author-Email: TryCua <gh@trycua.com>
Requires-Python: <3.14,>=3.12
Requires-Dist: httpx>=0.27.0
Requires-Dist: aiohttp>=3.9.3
Requires-Dist: asyncio
Requires-Dist: anyio>=4.4.1
Requires-Dist: typing-extensions>=4.12.2
Requires-Dist: pydantic>=2.6.4
Requires-Dist: rich>=13.7.1
Requires-Dist: python-dotenv>=1.0.1
Requires-Dist: cua-computer<0.6.0,>=0.5.0
Requires-Dist: cua-core<0.2.0,>=0.1.8
Requires-Dist: certifi>=2024.2.2
Requires-Dist: litellm>=1.74.12
Provides-Extra: openai
Provides-Extra: anthropic
Provides-Extra: qwen
Requires-Dist: qwen-vl-utils; extra == "qwen"
Requires-Dist: qwen-agent; extra == "qwen"
Requires-Dist: Pillow>=10.0.0; extra == "qwen"
Provides-Extra: omni
Requires-Dist: cua-som<0.2.0,>=0.1.0; extra == "omni"
Provides-Extra: uitars
Provides-Extra: uitars-mlx
Requires-Dist: mlx-vlm>=0.1.27; sys_platform == "darwin" and extra == "uitars-mlx"
Provides-Extra: uitars-hf
Requires-Dist: accelerate; extra == "uitars-hf"
Requires-Dist: torch; extra == "uitars-hf"
Requires-Dist: transformers>=4.54.0; extra == "uitars-hf"
Provides-Extra: glm45v-hf
Requires-Dist: accelerate; extra == "glm45v-hf"
Requires-Dist: torch; extra == "glm45v-hf"
Requires-Dist: transformers-v4.55.0-GLM-4.5V-preview; extra == "glm45v-hf"
Provides-Extra: opencua-hf
Requires-Dist: accelerate; extra == "opencua-hf"
Requires-Dist: torch; extra == "opencua-hf"
Requires-Dist: transformers>=4.53.0; extra == "opencua-hf"
Requires-Dist: tiktoken>=0.11.0; extra == "opencua-hf"
Requires-Dist: blobfile>=3.0.0; extra == "opencua-hf"
Provides-Extra: internvl-hf
Requires-Dist: accelerate; extra == "internvl-hf"
Requires-Dist: torch; extra == "internvl-hf"
Requires-Dist: transformers>=4.55.0; extra == "internvl-hf"
Requires-Dist: einops; extra == "internvl-hf"
Requires-Dist: timm; extra == "internvl-hf"
Provides-Extra: moondream3
Requires-Dist: accelerate; extra == "moondream3"
Requires-Dist: torch; extra == "moondream3"
Requires-Dist: transformers>=4.55.0; extra == "moondream3"
Provides-Extra: ui
Requires-Dist: gradio>=5.23.3; extra == "ui"
Requires-Dist: python-dotenv>=1.0.1; extra == "ui"
Provides-Extra: cli
Requires-Dist: yaspin>=3.1.0; extra == "cli"
Provides-Extra: hud
Requires-Dist: hud-python==0.4.52; extra == "hud"
Provides-Extra: gemini
Requires-Dist: google-genai>=1.41.0; extra == "gemini"
Provides-Extra: all
Requires-Dist: mlx-vlm>=0.1.27; sys_platform == "darwin" and extra == "all"
Requires-Dist: accelerate; extra == "all"
Requires-Dist: torch; extra == "all"
Requires-Dist: transformers>=4.55.0; extra == "all"
Requires-Dist: einops; extra == "all"
Requires-Dist: timm; extra == "all"
Requires-Dist: tiktoken>=0.11.0; extra == "all"
Requires-Dist: blobfile>=3.0.0; extra == "all"
Requires-Dist: gradio>=5.23.3; extra == "all"
Requires-Dist: python-dotenv>=1.0.1; extra == "all"
Requires-Dist: yaspin>=3.1.0; extra == "all"
Requires-Dist: google-genai>=1.41.0; extra == "all"
Requires-Dist: qwen-vl-utils; extra == "all"
Requires-Dist: qwen-agent; extra == "all"
Requires-Dist: Pillow>=10.0.0; extra == "all"
